digitaltwin_on_fhir/__init__.py
digitaltwin_on_fhir/core/__init__.py
digitaltwin_on_fhir/core/base.py
digitaltwin_on_fhir/core/digitaltwin.py
digitaltwin_on_fhir/core/lib.py
digitaltwin_on_fhir/core/loader.py
digitaltwin_on_fhir/core/operator.py
digitaltwin_on_fhir/core/search.py
digitaltwin_on_fhir/core/utils.py
digitaltwin_on_fhir/core/digital_twins/__init__.py
digitaltwin_on_fhir/core/digital_twins/digital_twins.py
digitaltwin_on_fhir/core/digital_twins/knowledgebase.py
digitaltwin_on_fhir/core/digital_twins/measurements.py
digitaltwin_on_fhir/core/digital_twins/process.py
digitaltwin_on_fhir/core/digital_twins/workflow.py
digitaltwin_on_fhir/core/digital_twins/workflow_tool.py
digitaltwin_on_fhir/core/exception/custom_error.py
digitaltwin_on_fhir/core/nzbase/Patient.py
digitaltwin_on_fhir/core/resource/__init__.py
digitaltwin_on_fhir/core/resource/abstract_resource.py
digitaltwin_on_fhir/core/resource/activity_definition.py
digitaltwin_on_fhir/core/resource/appointment.py
digitaltwin_on_fhir/core/resource/composition.py
digitaltwin_on_fhir/core/resource/consent.py
digitaltwin_on_fhir/core/resource/definition.py
digitaltwin_on_fhir/core/resource/element.py
digitaltwin_on_fhir/core/resource/encounter.py
digitaltwin_on_fhir/core/resource/endpoint.py
digitaltwin_on_fhir/core/resource/group.py
digitaltwin_on_fhir/core/resource/imaging_study.py
digitaltwin_on_fhir/core/resource/observation.py
digitaltwin_on_fhir/core/resource/patient.py
digitaltwin_on_fhir/core/resource/plan_definition.py
digitaltwin_on_fhir/core/resource/practitioner.py
digitaltwin_on_fhir/core/resource/procedure.py
digitaltwin_on_fhir/core/resource/research_study.py
digitaltwin_on_fhir/core/resource/research_subject.py
digitaltwin_on_fhir/core/resource/task.py
digitaltwin_on_fhir-1.1.1.dist-info/LICENSE
digitaltwin_on_fhir-1.1.1.dist-info/WHEEL
digitaltwin_on_fhir-1.1.1.dist-info/METADATA
digitaltwin_on_fhir-1.1.1.dist-info/RECORD
