Metadata-Version: 2.1
Name: digitaltwin-on-fhir
Version: 1.1.1
Summary: An adapter for transfer DigitalTWIN Clinic Description to FHIR
Keywords: fhir,DigitalTWIN,SPARC,Clinic Description
Author-email: Linkun Gao <gaolinkun123@gmail.com>
Requires-Python: >=3.9
Classifier: Development Status :: 5 - Production/Stable
Classifier: Environment :: Web Environment
Classifier: Intended Audience :: Developers
Classifier: Operating System :: OS Independent
Classifier: Programming Language :: Python
Classifier: Programming Language :: Python :: 3
Classifier: Programming Language :: Python :: 3.9
Classifier: Programming Language :: Python :: 3.10
Classifier: Programming Language :: Python :: 3.11
Classifier: Programming Language :: Python :: 3.12
Classifier: Topic :: Internet :: WWW/HTTP
Classifier: Topic :: Software Development :: Libraries :: Python Modules
Requires-Dist: fhirpy==2.0.5
Requires-Dist: pytest>=6.2.4 ; extra == "test"
Project-URL: Documentation, https://github.com/Copper3D-brids/digitalTwinOnFHIR#readme
Project-URL: Homepage, https://github.com/Copper3D-brids/digitalTwinOnFHIR
Project-URL: Source, https://github.com/Copper3D-brids/digitalTwinOnFHIR.git
Provides-Extra: test
